fdm_cli/__init__.py
fdm_cli/__main__.py
fdm_cli/commands.py
fdm_cli/utils.py
fdm_cli-0.0.1.dist-info/LICENCE
fdm_cli-0.0.1.dist-info/METADATA
fdm_cli-0.0.1.dist-info/WHEEL
fdm_cli-0.0.1.dist-info/entry_points.txt
fdm_cli-0.0.1.dist-info/top_level.txt
fdm_cli-0.0.1.dist-info/RECORD
