Metadata-Version: 2.2
Name: fdm-cli
Version: 0.0.1
Summary: A CLI tool that manages files and directories.
Author-email: Ayoub Aberbach <aberbach.me@gmail.com>
Maintainer-email: Ayoub Aberbach <aberbach.me@gmail.com>
Project-URL: Homepage, https://pypi.org/project/fdm-cli/
Project-URL: Repository, https://github.com/ayoub-aberbach/fdm_cli
Keywords: cli,file i/o,files,directories,file manager
Requires-Python: >=3.6
License-File: LICENCE
Requires-Dist: click
Requires-Dist: colorama
Requires-Dist: importlib-metadata; python_version < "3.12"
